mydesk/__init__.py
mydesk/gui.py
mydesk-2.0.0.dist-info/METADATA
mydesk-2.0.0.dist-info/WHEEL
mydesk-2.0.0.dist-info/entry_points.txt
mydesk-2.0.0.dist-info/top_level.txt
mydesk-2.0.0.dist-info/RECORD
