Metadata-Version: 2.1
Name: mydesk
Version: 2.0.0
Summary: UNKNOWN
Home-page: UNKNOWN
License: UNKNOWN
Platform: UNKNOWN
Requires-Python: >=3.8
Requires-Dist: selenium
Requires-Dist: gooey
Requires-Dist: retry
